<plan descriptions="./plans/TaskDescriptions.xml">
   <par name="event3" x="1626.9687994535843" y="-208.3189280982683" collapsed="false" id="5c8b089d-ff29-4f3a-bf3e-18e7a55261d5"> 
         <par name="perception" x="1474.9839509687358" y="-96.42498870432902" collapsed="true" id="6f0aa5b9-8224-44d2-a67f-f1371b806012"> 
               <tsk name="LocalizationTrack" x="1328.983950968736" y="-38.42498870432911" test_time="-1" test_result="true" id="40ba7dc1-938e-4b89-87c8-c99a5c0d0d90" />
               <tsk name="ObstacleDetection" x="1379.983950968736" y="9.57501129567126" test_time="-1" test_result="true" id="147672ff-a161-49e5-833a-8ad610030bd4" />
               <tsk name="PathPlanning" x="1530.5721862628538" y="14.57501129567143" test_time="-1" test_result="true" id="fa13fb3d-64a0-48e0-b8aa-71237e15f169" />
         </par>
         <par name="ProgressControl" x="1735.2187994535843" y="-91.31892809826834" collapsed="false" id="8f02c595-70d7-4065-b4e7-dcf29c64bbaa"> 
               <tsk name="Monitor(target=LiveLock)" x="1627.5521327869178" y="-23.98559476493486" test_time="-1" test_result="true" id="d8c0f6f3-6bc8-4475-a05f-2ec404e1f7a3" />
            <dec name="!L!" x="1823.2957932818051" y="-43.29549376904404"> 
                  <seq name="mission" x="1811.4915267263116" y="12.75466497532463" collapsed="false" id="efec6155-847e-46d1-8972-36fbe77140a5"> 
                        <tsk name="StandUp" x="1669.324282206126" y="118.15380178622607" test_time="100" test_result="true" id="7d3bd815-33ab-4d1e-970b-197f2f8cc6d8" />
                        <tsk name="PerceptionCalibration" x="1742.7591297591243" y="117.44413919413083" test_time="0" test_result="true" id="4f9d42c7-a5f6-4160-9279-dc840ebef143" />
                        <par name="StandingUp" x="1895.7633257493378" y="116.87333739978746" collapsed="false" id="35bca9b4-8ea9-4379-b273-e8bf7122be90"> 
                              <tsk name="Monitor(target=Falling)" x="1787.9451439311556" y="168.14606467251386" test_time="-1" test_result="true" id="00e76b34-96d4-4e03-a36a-8f0089d50334" />
                           <dec name="!L!" x="1981.7633257493378" y="165.87333739978712"> 
                                 <seq name="CollectObjects" x="1950.0230660090779" y="223.79541532186445" collapsed="false" id="2dba07e1-37c9-4583-82c5-9d636131d5e2"> 
                                       <sel name="GetObjectHoseIfNotYetInHand" x="1319.1063993424111" y="424.4303359567863" collapsed="true" id="dc55dd79-bce0-4b04-870d-7c53fa677ed1"> 
                                             <tsk name="isObjectInHand(target=right)" x="1151.2687925048049" y="525.5670880935371" test_time="10" test_result="false" id="80cd31a4-f152-4b41-9621-932d89cfe722" />
                                             <seq name="GetObjectHose" x="1349.8904902515012" y="527.8672046436512" collapsed="false" id="ccb52af9-40c8-4583-9d5e-2aeca47c23db"> 
                                                   <seq name="SearchObjectAndGo" x="1240.7864159564915" y="621.274467384356" collapsed="false" id="520e2328-10a3-4a4b-b5d6-f83d6a0c8c42"> 
                                                      <dec name="!L!" x="1197.490573968508" y="699.8182079358463"> 
                                                            <par name="SearchObjectWithStabilization" x="1128.899664877598" y="762.7272988449364" collapsed="false" id="67b36bb4-63c0-49ee-b346-6d0c18465a25"> 
                                                                  <seq name="Stabilization" x="1056.0038374239125" y="823.3747559846362" collapsed="false" id="7a36e994-5375-49e6-8332-cf0e6c49dc92"> 
                                                                        <tsk name="Monitor(target=Stable)" x="909.253837423913" y="878.1247559846364" test_time="0" test_result="true" id="94639728-cbe2-4442-adf2-388a33b6f8e8" />
                                                                        <tsk name="PostureControl(pose=stabilization)" x="1107.7730681931437" y="893.3747559846364" test_time="0" test_result="true" id="0f698639-2574-4407-b735-6af363949368" />
                                                                  </seq>
                                                                  <sel name="OperatorObjectValidation" x="1187.0698280477638" y="837.8236469412813" collapsed="false" id="622a4b9c-f0a0-4b00-a2b6-4f894359ad7f"> 
                                                                        <tsk name="SearchObject(target=Hose)" x="1091.5240810691562" y="961.2388224737052" test_time="0" test_result="true" id="335da43e-4bfd-435a-97a6-998ad9db6831" />
                                                                        <par name="OperatorCheckPoint" x="1290.7841404542128" y="964.0239401338273" collapsed="true" id="ec50fd2b-6585-4768-87c9-7fc610d5f40e"> 
                                                                           <dec name="L" x="1265.0341404542137" y="1036.0239401338233"> 
                                                                                 <seq name="Stabilization" x="1234.5341404542141" y="1099.8989401338233" collapsed="true" id="a5650ce3-87e0-4924-bb51-9892d3d61b69"> 
                                                                                       <tsk name="Monitor(target=Stable)" x="1116.7841404542132" y="1180.2739401338247" test_time="0" test_result="true" id="afe6b9a4-a574-4500-bc8b-6906e1ed7c96" />
                                                                                       <tsk name="PostureControl(pose=stabilization)" x="1274.5341404542137" y="1179.8989401338247" test_time="0" test_result="true" id="895e7cb8-7ec3-4fe1-ab4a-ab97ef5d0631" />
                                                                                 </seq>
                                                                           </dec>
                                                                           <dec name="T" x="1417.1591404542128" y="1038.023940133823"> 
                                                                                 <par name="TimeControl" x="1386.6591404542135" y="1103.7739401338233" collapsed="false" id="9bf6c3d0-d07f-4f6b-a260-8f1d51040abb"> 
                                                                                       <seq name="OperatorRequest" x="1286.6591404542125" y="1185.773940133823" collapsed="false" id="9680d232-c376-4529-8a9b-68a94a0a2913"> 
                                                                                             <tsk name="PushHMI(data=panoramic_image)" x="1027.6591404542153" y="1244.7739401338247" test_time="0" test_result="true" id="ba94bed4-8349-404e-977e-34b87e9c5b01" />
                                                                                             <tsk name="PushHMI(data=occupancy_grid)" x="1074.6591404542144" y="1283.7739401338258" test_time="0" test_result="true" id="a5d90934-afec-4db2-b519-9f5f1a570787" />
                                                                                             <tsk name="PushHMI(data=path)" x="1174.6591404542144" y="1325.7739401338258" test_time="0" test_result="true" id="a1c98c9e-7dee-4903-9921-d67ba968cbaf" />
                                                                                             <tsk name="HMIResponce" x="1336.659140454213" y="1322.7739401338258" test_time="0" test_result="true" id="ee026b9c-ddd2-40f2-86a4-098c16b14005" />
                                                                                       </seq>
                                                                                       <tsk name="Monitor(target=Timeout)" x="1381.6591404542135" y="1231.7739401338247" test_time="0" test_result="true" id="3fc69d7e-1faf-45e5-9af8-dfe64ce7cfca" />
                                                                                 </par>
                                                                           </dec>
                                                                        </par>
                                                                  </sel>
                                                            </par>
                                                      </dec>
                                                         <par name="TrackObjectAndGoToIt" x="1417.5591432292197" y="756.1835582934472" collapsed="false" id="e641c623-b9f6-4b21-8e8e-514cfbccc0a0"> 
                                                               <tsk name="TrackObject(target=Hose)" x="1358.8722745423493" y="838.052245162129" test_time="0" test_result="true" id="b178f320-49b1-4faa-91b5-23d6813f0003" />
                                                               <seq name="SearchPathAndGo" x="1527.244457914535" y="837.7919499018338" collapsed="false" id="800934e3-0237-46dd-9b11-f27f7e50371f"> 
                                                                     <par name="OperatorCheckPoint" x="1290.7841404542128" y="964.0239401338273" collapsed="true" id="ec50fd2b-6585-4768-87c9-7fc610d5f40e"> 
                                                                        <dec name="L" x="1265.0341404542137" y="1036.0239401338233"> 
                                                                              <seq name="Stabilization" x="1234.5341404542141" y="1099.8989401338233" collapsed="true" id="a5650ce3-87e0-4924-bb51-9892d3d61b69"> 
                                                                                    <tsk name="Monitor(target=Stable)" x="1116.7841404542132" y="1180.2739401338247" test_time="0" test_result="true" id="afe6b9a4-a574-4500-bc8b-6906e1ed7c96" />
                                                                                    <tsk name="PostureControl(pose=stabilization)" x="1274.5341404542137" y="1179.8989401338247" test_time="0" test_result="true" id="895e7cb8-7ec3-4fe1-ab4a-ab97ef5d0631" />
                                                                              </seq>
                                                                        </dec>
                                                                        <dec name="T" x="1417.1591404542128" y="1038.023940133823"> 
                                                                              <par name="TimeControl" x="1386.6591404542135" y="1103.7739401338233" collapsed="false" id="9bf6c3d0-d07f-4f6b-a260-8f1d51040abb"> 
                                                                                    <seq name="OperatorRequest" x="1286.6591404542125" y="1185.773940133823" collapsed="false" id="9680d232-c376-4529-8a9b-68a94a0a2913"> 
                                                                                          <tsk name="PushHMI(data=panoramic_image)" x="1027.6591404542153" y="1244.7739401338247" test_time="0" test_result="true" id="ba94bed4-8349-404e-977e-34b87e9c5b01" />
                                                                                          <tsk name="PushHMI(data=occupancy_grid)" x="1074.6591404542144" y="1283.7739401338258" test_time="0" test_result="true" id="a5d90934-afec-4db2-b519-9f5f1a570787" />
                                                                                          <tsk name="PushHMI(data=path)" x="1174.6591404542144" y="1325.7739401338258" test_time="0" test_result="true" id="a1c98c9e-7dee-4903-9921-d67ba968cbaf" />
                                                                                          <tsk name="HMIResponce" x="1336.659140454213" y="1322.7739401338258" test_time="0" test_result="true" id="ee026b9c-ddd2-40f2-86a4-098c16b14005" />
                                                                                    </seq>
                                                                                    <tsk name="Monitor(target=Timeout)" x="1381.6591404542135" y="1231.7739401338247" test_time="0" test_result="true" id="3fc69d7e-1faf-45e5-9af8-dfe64ce7cfca" />
                                                                              </par>
                                                                        </dec>
                                                                     </par>
                                                                     <tsk name="PerceptionCalibration" x="1468.674533799529" y="939.9488289488162" test_time="0" test_result="true" id="54bd310a-8b3e-4acc-baf4-57fe31ea05ff" />
                                                                     <tsk name="PathPlanningFocus(target=Hose)" x="1512.9367656068414" y="977.0996422095274" test_time="0" test_result="true" id="f0d48d3a-609a-4420-aec5-787e3b282eb6" />
                                                                     <tsk name="TurnTo(target=Hose)" x="1556.0136886837631" y="1014.022719132604" test_time="0" test_result="true" id="eebe2e74-4e14-44f9-9405-337147a65736" />
                                                                  <dec name="!L!" x="1733.057712775616" y="980.4919858562179"> 
                                                                        <swi name="Move" x="1727.0091099291844" y="1044.7965286564136" collapsed="false" id="940e2ef8-3885-49b7-92ec-d63d3ffe2471"> 
                                                                              <par name="AdvanceByWalkingAlongPath" x="1553.0091099291844" y="1116.7965286564145" collapsed="false" id="2c8e7c37-f3b5-4c8f-a2a5-3c5a267b8db8"> 
                                                                                 <dec name="!L!" x="1493.9086558865918" y="1172.0986774663113"> 
                                                                                       <seq name="PedestrianWalk" x="1456.5634177913541" y="1229.828836196469" collapsed="false" id="357dac3b-27fd-49fc-81be-abd75540c886"> 
                                                                                          <jnt x="1500.094766344764" y="1365.2131479631382" > 
                                                                                             <jnt x="2117.8566711066687" y="1367.4353701853636" > 
                                                                                                   <sel name="PathFollow" x="2140.6576430105833" y="1409.3392702069013" collapsed="false" id="944aa348-6c23-48fc-8e86-f5ffbe5e9f4c"> 
                                                                                                         <par name="Dynamic" x="1906.4072822602207" y="1564.4698618375037" collapsed="false" id="c62c576f-78bc-4e87-b611-98c41f13ce26"> 
                                                                                                            <dec name="F:1" x="1875.6850649350624" y="1608.089854589848"> 
                                                                                                                  <tsk name="whileDynamicWalk" x="1828.6295044824415" y="1657.803195170833" test_time="0" test_result="true" id="b4c6f4ca-277d-4d6d-bd85-9d750f52f7a8" />
                                                                                                            </dec>
                                                                                                               <sel name="Try" x="1970.3822843822845" y="1657.4119214119182" collapsed="false" id="5c14a900-5e51-4cff-abc7-e676fe221c09"> 
                                                                                                                     <seq name="DynamicWalkTask" x="1820.2711732711718" y="1715.6341436341386" collapsed="false" id="79cbd549-751d-40ee-8b20-d05ec87448e6"> 
                                                                                                                           <tsk name="DWStandUp" x="1779.2711732711718" y="1771.6341436341386" test_time="0" test_result="true" id="4f7aab64-539a-4b5a-80f8-46f0098e7a80" />
                                                                                                                           <tsk name="DynamicWalk" x="1871.6295044824426" y="1772.3587507263846" test_time="0" test_result="true" id="b262874d-f313-428b-b0ab-307da4d5ce23" />
                                                                                                                     </seq>
                                                                                                                     <tsk name="QuadWalk(mode=DEBRIS)" x="1943.5183933713286" y="1713.8031951708317" test_time="0" test_result="true" id="161b819e-2d6b-4bd8-83e8-0b5e7b616a66" />
                                                                                                               </sel>
                                                                                                         </par>
                                                                                                         <par name="Discrete" x="2139.296171149107" y="1564.0254173930598" collapsed="false" id="08f23f0a-0be6-4b70-90c9-ad1337e4e62a"> 
                                                                                                            <dec name="F:1" x="2096.685064935063" y="1607.7565212565146"> 
                                                                                                                  <tsk name="whileDiscreteWalk" x="2054.5183933713297" y="1655.3587507263915" test_time="0" test_result="true" id="60f61308-56a5-4335-a648-795690e62393" />
                                                                                                            </dec>
                                                                                                               <sel name="Try" x="2197.0489510489488" y="1655.189699189696" collapsed="false" id="5d0244bb-a35f-451c-ad77-a66d8e3e3c2b"> 
                                                                                                                     <seq name="DiscreteWalkTask" x="2120.2711732711714" y="1708.6341436341386" collapsed="false" id="0a5da691-eb1f-4465-8787-7a46d67fe678"> 
                                                                                                                           <tsk name="DWStandUp" x="2098.2711732711714" y="1772.6341436341386" test_time="0" test_result="true" id="467e98ae-cbdc-4ec4-976c-6c0cab8940a8" />
                                                                                                                           <tsk name="DiscreteWalk" x="2186.073948926888" y="1773.1365285041634" test_time="0" test_result="true" id="00607f67-1e5a-4174-8c5f-1980f00e0680" />
                                                                                                                     </seq>
                                                                                                                     <sel name="try_quads" x="2298.573948926887" y="1710.3031951708344" collapsed="false" id="11e38bcb-c2db-451d-8107-0016eace52ce"> 
                                                                                                                           <par name="Debris" x="2305.9628378157745" y="1769.9143062819471" collapsed="false" id="06a6691d-bb10-4701-942c-b9bd8827c7fd"> 
                                                                                                                              <dec name="F:1" x="2261.907287157283" y="1815.7565212565137"> 
                                                                                                                                    <tsk name="whileQuadWalkDEBRIS" x="2208.1850600379967" y="1863.2476396152765" test_time="0" test_result="true" id="12b76090-0766-4af5-aa5c-f87a8692c335" />
                                                                                                                              </dec>
                                                                                                                                 <tsk name="QuadWalk(mode=DEBRIS)" x="2357.851726704663" y="1866.1365285041634" test_time="0" test_result="true" id="99191540-18e7-4148-b56c-a4b0b994085b" />
                                                                                                                           </par>
                                                                                                                           <tsk name="QuadWalk(mode=HILLS)" x="2373.5183933713297" y="1770.247639615277" test_time="0" test_result="true" id="934886f6-fa30-4bbb-8538-26e4a0998150" />
                                                                                                                     </sel>
                                                                                                               </sel>
                                                                                                         </par>
                                                                                                         <par name="Quad_MUD" x="2374.8517267046614" y="1560.6920840597268" collapsed="false" id="1eb74863-3986-4aba-b8f3-1197ee16c3bb"> 
                                                                                                            <dec name="F:1" x="2332.2406204906174" y="1604.4231879231816"> 
                                                                                                                  <tsk name="whileQuadWalkMUD" x="2290.0739489268844" y="1652.0254173930584" test_time="0" test_result="true" id="0918f43a-0853-4ade-9014-5d74dd42261f" />
                                                                                                            </dec>
                                                                                                               <tsk name="QuadWalk(mode=MUD)" x="2421.629504482439" y="1651.8031951708308" test_time="0" test_result="true" id="218a31c2-d2de-41e5-bb1c-918d8c572707" />
                                                                                                         </par>
                                                                                                   </sel>
                                                                                             </jnt>
                                                                                          </jnt>
                                                                                       </seq>
                                                                                 </dec>
                                                                                    <par name="Exceptions" x="1694.193481113553" y="1174.6048314647126" collapsed="false" id="201a0ae9-fb4c-4c7a-91de-40ed30343ad0"> 
                                                                                       <dec name="F:1" x="1685.9671181045846" y="1222.5810219409063"> 
                                                                                             <tsk name="untilOperatorIntervention" x="1621.4959974378155" y="1279.5285852471523" test_time="0" test_result="true" id="fe2614e4-b2ee-4a95-8f3f-b4614d36afc3" />
                                                                                       </dec>
                                                                                       <dec name="F:1" x="1738.6776080976788" y="1223.4143552742376"> 
                                                                                             <tsk name="whileSolution" x="1709.8802943003725" y="1325.710700233619" test_time="0" test_result="true" id="f963520d-40e5-4fa6-8481-e05d72c46425" />
                                                                                       </dec>
                                                                                    </par>
                                                                              </par>
                                                                              <seq name="NoSolution" x="1817.6044469593023" y="1222.0582500268367" collapsed="true" id="82b116b7-28c0-487d-9f94-a6e86f4ece8b"> 
                                                                                    <par name="OperatorControlPoint" x="1787.7711136259666" y="1305.0582500268351" collapsed="false" id="763e7b55-6b81-48d3-8cc6-e33aa74bb5c2"> 
                                                                                       <dec name="L" x="1754.104446959298" y="1353.3915833601673"> 
                                                                                             <seq name="Stabilization" x="1723.1044469592991" y="1400.3915833601654" collapsed="false" id="8d1a4936-6662-44ef-843c-40f3ea40d56f"> 
                                                                                                   <tsk name="Monitor(target=Stable)" x="1682.104446959301" y="1441.391583360163" test_time="0" test_result="true" id="c991113c-fd03-426d-b64e-21a3ffca8a65" />
                                                                                                   <tsk name="PostureControl(pose=stabilization)" x="1734.1044469593007" y="1475.391583360162" test_time="0" test_result="true" id="3c8781ae-f955-4d08-a217-476f8e02828c" />
                                                                                             </seq>
                                                                                       </dec>
                                                                                       <dec name="T" x="1957.2711136259727" y="1355.724916693499"> 
                                                                                             <par name="TimeControl" x="1927.6044469593066" y="1453.5582500268326" collapsed="false" id="c3bba4ef-31b1-48bc-a8b4-366e0e30f02c"> 
                                                                                                   <seq name="OperatorRequest" x="1859.104446959305" y="1522.3915833601657" collapsed="false" id="ca149b95-ccbb-42e5-aa61-68c076b879c0"> 
                                                                                                         <tsk name="PushHMI(data=panoramic_image)" x="1824.1044469593032" y="1567.3915833601661" test_time="0" test_result="true" id="4b63e53f-26b7-41f2-a5f2-52ebad39f4e3" />
                                                                                                         <tsk name="HMIResponce" x="1966.104446959302" y="1601.3915833601661" test_time="0" test_result="true" id="3d7f22c5-cd26-445a-8982-faeb7af0666e" />
                                                                                                   </seq>
                                                                                                   <tsk name="Monitor(target=Timeout)" x="2019.2711136259663" y="1526.0582500268345" test_time="0" test_result="true" id="bbda0869-b84e-4332-b10a-30417d2b3a6c" />
                                                                                             </par>
                                                                                       </dec>
                                                                                    </par>
                                                                              </seq>
                                                                        </swi>
                                                                  </dec>
                                                               </seq>
                                                         </par>
                                                   </seq>
                                                   <tsk name="PickUp(target=Hose)" x="1469.4738499586326" y="621.3500834457406" test_time="100" test_result="true" id="920eb022-e4e8-4121-ab91-a4e2a1e827ef" />
                                             </seq>
                                       </sel>
                                       <par name="GoToObjectPipeAndConnectObjects" x="1910.9675104535238" y="378.05732008376924" collapsed="true" id="0b7d9b88-0324-4624-9dec-6e34cc2690ac"> 
                                             <tsk name="whileObjectInHands" x="1848.2099346959462" y="450.3805524070036" test_time="-1" test_result="true" id="028da48a-38c6-4d84-92c0-64ecab7083b3" />
                                             <seq name="GoToPipeAndConnect" x="2012.640220890219" y="450.6175491175451" collapsed="false" id="f22f07cc-0f15-446a-bfc3-3af20dafaf27"> 
                                                   <seq name="SearchObjectAndGo" x="1924.422779592857" y="501.0147271246177" collapsed="true" id="4536b2a0-591f-42fa-94fa-3ad01eab74cd"> 
                                                      <dec name="!L!" x="1881.1269376048733" y="579.5584676761065"> 
                                                            <par name="SearchObjectWithStabilization" x="1812.5360285139639" y="642.4675585851952" collapsed="false" id="ad175810-9e93-4cab-b27f-346b949ff88e"> 
                                                                  <seq name="Stabilization" x="1739.6402010602762" y="703.1150157249002" collapsed="false" id="f7907df1-3120-45fe-b07d-6816a2eb145b"> 
                                                                        <tsk name="Monitor(target=Stable)" x="1592.890201060275" y="757.8650157248966" test_time="0" test_result="true" id="a2ffbfcb-ddb2-4a01-9ea3-9706c66888b7" />
                                                                        <tsk name="PostureControl(pose=stabilization)" x="1791.409431829509" y="773.1150157248961" test_time="0" test_result="true" id="67ac7d0c-0b23-4675-a5ed-5465da8ab3e2" />
                                                                  </seq>
                                                                  <sel name="OperatorObjectValidation" x="1870.7061916841292" y="717.5639066815446" collapsed="false" id="67623ec2-df3a-4d64-8332-67e1cc60fa17"> 
                                                                        <tsk name="SearchObject(target=Hose)" x="1775.1604447055215" y="840.979082213965" test_time="0" test_result="true" id="33ffb703-2498-4634-88b4-ce14c01139bc" />
                                                                        <par name="OperatorCheckPoint" x="1974.420504090578" y="843.764199874087" collapsed="true" id="cfed5c14-823b-46f7-811c-9d41d6986b37"> 
                                                                           <dec name="L" x="1948.6705040905792" y="915.7641998740831"> 
                                                                                 <seq name="Stabilization" x="1918.1705040905795" y="979.6391998740831" collapsed="true" id="14658d12-f68f-4881-83df-a677be51e50d"> 
                                                                                       <tsk name="Monitor(target=Stable)" x="1800.420504090579" y="1060.0141998740844" test_time="0" test_result="true" id="0824987f-4f0e-4a29-bc99-8cfefa6d28d5" />
                                                                                       <tsk name="PostureControl(pose=stabilization)" x="1958.1705040905792" y="1059.6391998740844" test_time="0" test_result="true" id="ee003751-ed51-462d-8e61-fb1a1cfce169" />
                                                                                 </seq>
                                                                           </dec>
                                                                           <dec name="T" x="2100.795504090579" y="917.7641998740829"> 
                                                                                 <par name="TimeControl" x="2070.295504090579" y="983.5141998740831" collapsed="false" id="e75c1c3e-34f6-4791-9cd6-6af2053ad810"> 
                                                                                       <seq name="OperatorRequest" x="1970.295504090578" y="1065.5141998740828" collapsed="false" id="11dc746d-245a-475c-bc00-1e264f860761"> 
                                                                                             <tsk name="PushHMI(data=panoramic_image)" x="1711.295504090577" y="1124.5141998740844" test_time="0" test_result="true" id="e13d9d5f-220e-477e-bfb6-5b0e86ec7b33" />
                                                                                             <tsk name="PushHMI(data=occupancy_grid)" x="1758.2955040905795" y="1163.5141998740855" test_time="0" test_result="true" id="399f98a8-8380-45db-9a98-b7151c4d14d5" />
                                                                                             <tsk name="PushHMI(data=path)" x="1858.29550409058" y="1205.5141998740855" test_time="0" test_result="true" id="18051234-5c05-4bfa-a05f-a882b749018c" />
                                                                                             <tsk name="HMIResponce" x="2020.2955040905786" y="1202.5141998740855" test_time="0" test_result="true" id="3d435215-e96d-4153-8e28-ee09bdeb610c" />
                                                                                       </seq>
                                                                                       <tsk name="Monitor(target=Timeout)" x="2065.295504090579" y="1111.5141998740844" test_time="0" test_result="true" id="fe368561-3fc3-4e73-8cac-35d0068ddb3d" />
                                                                                 </par>
                                                                           </dec>
                                                                        </par>
                                                                  </sel>
                                                            </par>
                                                      </dec>
                                                         <par name="TrackObjectAndGoToIt" x="2101.195506865586" y="635.923818033706" collapsed="false" id="195a93de-2b44-45db-bf24-d284344e7618"> 
                                                               <tsk name="TrackObject(target=Pipe)" x="2042.5086381787144" y="717.7925049023924" test_time="0" test_result="true" id="78bcf8a1-79ee-4d31-be2c-de1751fa825f" />
                                                               <seq name="SearchPathAndGo" x="2210.8808215509007" y="717.5322096420972" collapsed="false" id="411d4701-9137-44c1-b3e3-b8b24cfbaf25"> 
                                                                     <par name="OperatorCheckPoint" x="1974.420504090578" y="843.764199874087" collapsed="true" id="cfed5c14-823b-46f7-811c-9d41d6986b37"> 
                                                                        <dec name="L" x="1948.6705040905792" y="915.7641998740831"> 
                                                                              <seq name="Stabilization" x="1918.1705040905795" y="979.6391998740831" collapsed="true" id="14658d12-f68f-4881-83df-a677be51e50d"> 
                                                                                    <tsk name="Monitor(target=Stable)" x="1800.420504090579" y="1060.0141998740844" test_time="0" test_result="true" id="0824987f-4f0e-4a29-bc99-8cfefa6d28d5" />
                                                                                    <tsk name="PostureControl(pose=stabilization)" x="1958.1705040905792" y="1059.6391998740844" test_time="0" test_result="true" id="ee003751-ed51-462d-8e61-fb1a1cfce169" />
                                                                              </seq>
                                                                        </dec>
                                                                        <dec name="T" x="2100.795504090579" y="917.7641998740829"> 
                                                                              <par name="TimeControl" x="2070.295504090579" y="983.5141998740831" collapsed="false" id="e75c1c3e-34f6-4791-9cd6-6af2053ad810"> 
                                                                                    <seq name="OperatorRequest" x="1970.295504090578" y="1065.5141998740828" collapsed="false" id="11dc746d-245a-475c-bc00-1e264f860761"> 
                                                                                          <tsk name="PushHMI(data=panoramic_image)" x="1711.295504090577" y="1124.5141998740844" test_time="0" test_result="true" id="e13d9d5f-220e-477e-bfb6-5b0e86ec7b33" />
                                                                                          <tsk name="PushHMI(data=occupancy_grid)" x="1758.2955040905795" y="1163.5141998740855" test_time="0" test_result="true" id="399f98a8-8380-45db-9a98-b7151c4d14d5" />
                                                                                          <tsk name="PushHMI(data=path)" x="1858.29550409058" y="1205.5141998740855" test_time="0" test_result="true" id="18051234-5c05-4bfa-a05f-a882b749018c" />
                                                                                          <tsk name="HMIResponce" x="2020.2955040905786" y="1202.5141998740855" test_time="0" test_result="true" id="3d435215-e96d-4153-8e28-ee09bdeb610c" />
                                                                                    </seq>
                                                                                    <tsk name="Monitor(target=Timeout)" x="2065.295504090579" y="1111.5141998740844" test_time="0" test_result="true" id="fe368561-3fc3-4e73-8cac-35d0068ddb3d" />
                                                                              </par>
                                                                        </dec>
                                                                     </par>
                                                                     <tsk name="PerceptionCalibration" x="2152.3108974358943" y="819.6890886890759" test_time="0" test_result="true" id="eca2bb63-67df-4ba1-8230-4e6c3e5c86b1" />
                                                                     <tsk name="PathPlanningFocus(target=Pipe)" x="2196.5731292432065" y="856.8399019497871" test_time="0" test_result="true" id="ed358763-f9c2-4525-8f1f-053b73ee549c" />
                                                                     <tsk name="TurnTo(target=Pipe)" x="2239.650052320129" y="893.7629788728638" test_time="0" test_result="true" id="94027543-805e-4083-ab6e-eaa9870b66cc" />
                                                                  <dec name="!L!" x="2416.6940764119754" y="860.2322455964776"> 
                                                                        <swi name="Move" x="2410.645473565544" y="924.5367883966734" collapsed="false" id="cd717a3b-55f9-433f-99b3-9adbe2b11d77"> 
                                                                              <par name="AdvanceByWalkingAlongPath" x="2236.6454735655498" y="996.5367883966743" collapsed="false" id="47e5977d-b0d7-40d7-b27e-e26de00085b7"> 
                                                                                 <dec name="!L!" x="2177.5450195229573" y="1051.838937206571"> 
                                                                                       <seq name="PedestrianWalk" x="2139.19978142772" y="1116.2357626033956" collapsed="false" id="8f7dddec-df5a-4f65-80e0-da90d828622a"> 
                                                                                             <sel name="PathFollow" x="2140.6576430105833" y="1409.3392702069013" collapsed="false" id="944aa348-6c23-48fc-8e86-f5ffbe5e9f4c"> 
                                                                                                   <par name="Dynamic" x="1906.4072822602207" y="1564.4698618375037" collapsed="false" id="c62c576f-78bc-4e87-b611-98c41f13ce26"> 
                                                                                                      <dec name="F:1" x="1875.6850649350624" y="1608.089854589848"> 
                                                                                                            <tsk name="whileDynamicWalk" x="1828.6295044824415" y="1657.803195170833" test_time="0" test_result="true" id="b4c6f4ca-277d-4d6d-bd85-9d750f52f7a8" />
                                                                                                      </dec>
                                                                                                         <sel name="Try" x="1970.3822843822845" y="1657.4119214119182" collapsed="false" id="5c14a900-5e51-4cff-abc7-e676fe221c09"> 
                                                                                                               <seq name="DynamicWalkTask" x="1820.2711732711718" y="1715.6341436341386" collapsed="false" id="79cbd549-751d-40ee-8b20-d05ec87448e6"> 
                                                                                                                     <tsk name="DWStandUp" x="1779.2711732711718" y="1771.6341436341386" test_time="0" test_result="true" id="4f7aab64-539a-4b5a-80f8-46f0098e7a80" />
                                                                                                                     <tsk name="DynamicWalk" x="1871.6295044824426" y="1772.3587507263846" test_time="0" test_result="true" id="b262874d-f313-428b-b0ab-307da4d5ce23" />
                                                                                                               </seq>
                                                                                                               <tsk name="QuadWalk(mode=DEBRIS)" x="1943.5183933713286" y="1713.8031951708317" test_time="0" test_result="true" id="161b819e-2d6b-4bd8-83e8-0b5e7b616a66" />
                                                                                                         </sel>
                                                                                                   </par>
                                                                                                   <par name="Discrete" x="2139.296171149107" y="1564.0254173930598" collapsed="false" id="08f23f0a-0be6-4b70-90c9-ad1337e4e62a"> 
                                                                                                      <dec name="F:1" x="2096.685064935063" y="1607.7565212565146"> 
                                                                                                            <tsk name="whileDiscreteWalk" x="2054.5183933713297" y="1655.3587507263915" test_time="0" test_result="true" id="60f61308-56a5-4335-a648-795690e62393" />
                                                                                                      </dec>
                                                                                                         <sel name="Try" x="2197.0489510489488" y="1655.189699189696" collapsed="false" id="5d0244bb-a35f-451c-ad77-a66d8e3e3c2b"> 
                                                                                                               <seq name="DiscreteWalkTask" x="2120.2711732711714" y="1708.6341436341386" collapsed="false" id="0a5da691-eb1f-4465-8787-7a46d67fe678"> 
                                                                                                                     <tsk name="DWStandUp" x="2098.2711732711714" y="1772.6341436341386" test_time="0" test_result="true" id="467e98ae-cbdc-4ec4-976c-6c0cab8940a8" />
                                                                                                                     <tsk name="DiscreteWalk" x="2186.073948926888" y="1773.1365285041634" test_time="0" test_result="true" id="00607f67-1e5a-4174-8c5f-1980f00e0680" />
                                                                                                               </seq>
                                                                                                               <sel name="try_quads" x="2298.573948926887" y="1710.3031951708344" collapsed="false" id="11e38bcb-c2db-451d-8107-0016eace52ce"> 
                                                                                                                     <par name="Debris" x="2305.9628378157745" y="1769.9143062819471" collapsed="false" id="06a6691d-bb10-4701-942c-b9bd8827c7fd"> 
                                                                                                                        <dec name="F:1" x="2261.907287157283" y="1815.7565212565137"> 
                                                                                                                              <tsk name="whileQuadWalkDEBRIS" x="2208.1850600379967" y="1863.2476396152765" test_time="0" test_result="true" id="12b76090-0766-4af5-aa5c-f87a8692c335" />
                                                                                                                        </dec>
                                                                                                                           <tsk name="QuadWalk(mode=DEBRIS)" x="2357.851726704663" y="1866.1365285041634" test_time="0" test_result="true" id="99191540-18e7-4148-b56c-a4b0b994085b" />
                                                                                                                     </par>
                                                                                                                     <tsk name="QuadWalk(mode=HILLS)" x="2373.5183933713297" y="1770.247639615277" test_time="0" test_result="true" id="934886f6-fa30-4bbb-8538-26e4a0998150" />
                                                                                                               </sel>
                                                                                                         </sel>
                                                                                                   </par>
                                                                                                   <par name="Quad_MUD" x="2374.8517267046614" y="1560.6920840597268" collapsed="false" id="1eb74863-3986-4aba-b8f3-1197ee16c3bb"> 
                                                                                                      <dec name="F:1" x="2332.2406204906174" y="1604.4231879231816"> 
                                                                                                            <tsk name="whileQuadWalkMUD" x="2290.0739489268844" y="1652.0254173930584" test_time="0" test_result="true" id="0918f43a-0853-4ade-9014-5d74dd42261f" />
                                                                                                      </dec>
                                                                                                         <tsk name="QuadWalk(mode=MUD)" x="2421.629504482439" y="1651.8031951708308" test_time="0" test_result="true" id="218a31c2-d2de-41e5-bb1c-918d8c572707" />
                                                                                                   </par>
                                                                                             </sel>
                                                                                       </seq>
                                                                                 </dec>
                                                                                    <par name="Exceptions" x="2377.829844749912" y="1054.3450912049723" collapsed="false" id="b8bccfba-eea5-40cd-93f7-2c67a736a443"> 
                                                                                       <dec name="F:1" x="2369.6034817409436" y="1102.321281681166"> 
                                                                                             <tsk name="untilOperatorIntervention" x="2305.132361074174" y="1159.268844987412" test_time="0" test_result="true" id="1fabea8b-20d7-4f8c-9785-a750101b5e1a" />
                                                                                       </dec>
                                                                                       <dec name="F:1" x="2422.313971734038" y="1103.1546150144973"> 
                                                                                             <tsk name="whileSolution" x="2393.5166579367315" y="1205.4509599738788" test_time="0" test_result="true" id="02e3c874-de1f-42d7-a400-b4fbaf238173" />
                                                                                       </dec>
                                                                                    </par>
                                                                              </par>
                                                                              <seq name="NoSolution" x="2501.240810595662" y="1101.7985097670964" collapsed="true" id="0f83845a-5b75-4172-ba3f-e1c44a9f6785"> 
                                                                                    <par name="OperatorControlPoint" x="2471.407477262326" y="1184.7985097670949" collapsed="false" id="1dc80a69-9183-4dfa-a075-327eca19ecfd"> 
                                                                                       <dec name="L" x="2437.7408105956574" y="1233.131843100427"> 
                                                                                             <seq name="Stabilization" x="2406.7408105956583" y="1280.1318431004252" collapsed="false" id="42885568-de89-416e-8898-0c1ba17278f0"> 
                                                                                                   <tsk name="Monitor(target=Stable)" x="2365.7408105956597" y="1321.1318431004227" test_time="0" test_result="true" id="f67dc3c2-688c-4fd2-b04c-c92cf577dbca" />
                                                                                                   <tsk name="PostureControl(pose=stabilization)" x="2417.74081059566" y="1355.1318431004217" test_time="0" test_result="true" id="ea83096e-ad60-481e-94f9-780147895e61" />
                                                                                             </seq>
                                                                                       </dec>
                                                                                       <dec name="T" x="2640.9074772623326" y="1235.4651764337586"> 
                                                                                             <par name="TimeControl" x="2611.2408105956656" y="1333.2985097670924" collapsed="false" id="596e5377-b7ed-4ed7-8a67-ba4d7468889d"> 
                                                                                                   <seq name="OperatorRequest" x="2542.7408105956647" y="1402.1318431004254" collapsed="false" id="946c2fe6-fca0-4afb-b170-925a97bd0ae3"> 
                                                                                                         <tsk name="PushHMI(data=panoramic_image)" x="2507.740810595663" y="1447.1318431004258" test_time="0" test_result="true" id="f32712e6-b387-4808-8279-fd2ee44fa2f6" />
                                                                                                         <tsk name="HMIResponce" x="2649.740810595662" y="1481.1318431004258" test_time="0" test_result="true" id="a9966a97-f1f0-4179-a177-a0c8fb24cdd5" />
                                                                                                   </seq>
                                                                                                   <tsk name="Monitor(target=Timeout)" x="2702.907477262328" y="1405.7985097670942" test_time="0" test_result="true" id="5daa6ba3-8d6b-418a-981d-c3c3569d5e53" />
                                                                                             </par>
                                                                                       </dec>
                                                                                    </par>
                                                                              </seq>
                                                                        </swi>
                                                                  </dec>
                                                               </seq>
                                                         </par>
                                                   </seq>
                                                   <seq name="ConnectObjects" x="2147.4136800819742" y="502.6635808680568" collapsed="true" id="6c3bbe76-eddc-472f-8155-7b86be16477e"> 
                                                         <par name="StabilizationDuringObjectsConnection" x="2123.5807860668056" y="567.0731930996461" collapsed="false" id="da44f646-3657-4638-a81e-b10ed44485b9"> 
                                                            <dec name="L" x="2030.2474527334712" y="632.0731930996425"> 
                                                                  <seq name="Stabilization" x="1997.5807860668017" y="699.0731930996409" collapsed="false" id="925e9a78-3abb-49f5-996d-64fad49a1562"> 
                                                                        <tsk name="Monitor(target=Stable)" x="1809.580786066802" y="781.0731930996384" test_time="-1" test_result="true" id="ac517a4d-fd30-4856-b5ee-38884830768d" />
                                                                        <tsk name="PostureControl(pose=stabilize)" x="1960.5807860668012" y="782.0731930996384" test_time="100" test_result="true" id="6f61e986-80c0-46f3-af58-d56cd312d0e8" />
                                                                  </seq>
                                                            </dec>
                                                            <dec name="!L!" x="2183.025230511254" y="664.7398597663079"> 
                                                                  <seq name="Connection" x="2161.5807860668083" y="823.739859766306" collapsed="false" id="647693bf-a290-482a-8286-24f13507e599"> 
                                                                        <tsk name="AlignObjects" x="1844.8371963232112" y="910.7655007919471" test_time="100" test_result="true" id="82f3d8d4-41b4-45f8-b4b5-5c41a2a83d52" />
                                                                        <par name="TimedOperatorRequest" x="1922.9545234405384" y="965.9519809784266" collapsed="true" id="621c7cf0-7009-4097-b1c4-e32e5247c528"> 
                                                                              <seq name="OperatorRequest" x="1781.9545234405396" y="1014.9519809784266" collapsed="false" id="b73326c0-f44d-4331-8683-2f632acda86b"> 
                                                                                    <tsk name="PushHMI(data=objects)" x="1690.9545234405387" y="1087.9519809784254" test_time="100" test_result="true" id="59939481-08dc-420b-8a7f-c5c68082699a" />
                                                                                    <tsk name="HMIResponse" x="1867.9545234405393" y="1087.9519809784254" test_time="100" test_result="true" id="6b0b4bc4-9354-4f8c-b909-d3e9db9505f1" />
                                                                              </seq>
                                                                              <tsk name="Monitor(target=Timeout)" x="1933.9545234405384" y="1015.9519809784266" test_time="-1" test_result="true" id="a49f2d9c-6084-4d58-85cd-66b3eab8270d" />
                                                                        </par>
                                                                        <tsk name="ObjectAttachment" x="2097.803008289027" y="928.5176375440841" test_time="100" test_result="true" id="af786d58-9eb7-43a5-83c0-4ac6e0229705" />
                                                                        <par name="TimedOperatorRequest" x="2237.1767456627667" y="972.2045062309522" collapsed="true" id="9c826852-0d78-41a5-8d25-8985263c9306"> 
                                                                              <tsk name="Monitor(target=Timeout)" x="2132.1767456627667" y="1028.2045062309521" test_time="-1" test_result="true" id="ab5bca53-6443-4ccd-95f0-aab49a242c41" />
                                                                              <seq name="OperatorRequest" x="2305.1767456627585" y="1027.2045062309521" collapsed="false" id="b806f8a2-98a6-4dde-b087-e6eed50aa7ec"> 
                                                                                    <tsk name="PushHMI(data=objects)" x="2214.176745662766" y="1100.2045062309503" test_time="100" test_result="true" id="d1839b1a-a7cb-4305-9019-7f8f4f8157fd" />
                                                                                    <tsk name="HMIResponse" x="2391.1767456627604" y="1100.2045062309503" test_time="100" test_result="true" id="7aaaef22-0aae-4c48-acbd-83a007f3c18f" />
                                                                              </seq>
                                                                        </par>
                                                                        <sel name="ConnectionValidation" x="2462.136341622357" y="909.2954153218622" collapsed="false" id="d95fba33-665f-49d8-ac92-7457fba8dec7"> 
                                                                              <tsk name="ValidateConnection" x="2408.1363416223567" y="984.2954153218617" test_time="100" test_result="true" id="59037b7b-a5b0-48fb-aaaf-0b5117ef83ea" />
                                                                           <dec name="F" x="2566.1363416223567" y="942.2954153218619"> 
                                                                                 <tsk name="ReverseAttachment" x="2557.136341622356" y="983.2954153218617" test_time="100" test_result="true" id="77b375d6-7ca5-4451-8ddd-baa817c3438e" />
                                                                           </dec>
                                                                        </sel>
                                                                  </seq>
                                                            </dec>
                                                         </par>
                                                   </seq>
                                             </seq>
                                       </par>
                                       <seq name="GoToObjectSpigotAndOpen" x="2603.6177893525783" y="423.00150310451625" collapsed="true" id="b669cc8c-091f-4973-9622-1b704f38ddb2"> 
                                             <seq name="SearchObjectAndGo" x="2548.362173532249" y="526.1662422761309" collapsed="true" id="2e150175-239d-43c1-9d05-b31c334e1346"> 
                                                <dec name="!L!" x="2505.066331544266" y="604.7099828276213"> 
                                                      <par name="SearchObjectWithStabilization" x="2436.475422453357" y="667.6190737367114" collapsed="false" id="3a450cd2-236f-4357-abe7-8dafe3cc0d16"> 
                                                            <seq name="Stabilization" x="2363.5795949996705" y="728.2665308764159" collapsed="false" id="e6d75fec-7077-4aeb-8339-2356215cd464"> 
                                                                  <tsk name="Monitor(target=Stable)" x="2216.829594999672" y="783.0165308764134" test_time="0" test_result="true" id="c2363075-a721-473c-8864-296985720831" />
                                                                  <tsk name="PostureControl(pose=stabilization)" x="2415.348825768902" y="798.2665308764118" test_time="0" test_result="true" id="446f1fca-ece7-4b4f-9180-837e61b0f1d9" />
                                                            </seq>
                                                            <sel name="OperatorObjectValidation" x="2494.6455856235216" y="742.7154218330612" collapsed="false" id="e9c78857-c181-4a0c-8772-740d2ded5306"> 
                                                                  <tsk name="SearchObject(target=Spigot)" x="2399.099838644914" y="866.1305973654806" test_time="0" test_result="true" id="16b20e4c-e8f9-4e8b-a5eb-ba8546259d78" />
                                                                  <par name="OperatorCheckPoint" x="2598.3598980299703" y="868.9157150256027" collapsed="true" id="81d5fc0e-0ec0-485a-a70d-39883e2686f9"> 
                                                                     <dec name="L" x="2572.609898029971" y="940.9157150255988"> 
                                                                           <seq name="Stabilization" x="2542.109898029971" y="1004.7907150255988" collapsed="true" id="080f208e-28c9-48b8-8754-1bd9ccc4ca57"> 
                                                                                 <tsk name="Monitor(target=Stable)" x="2424.359898029972" y="1085.1657150256" test_time="0" test_result="true" id="4382b9bf-54e7-419a-851e-0a07c63d2a76" />
                                                                                 <tsk name="PostureControl(pose=stabilization)" x="2582.1098980299707" y="1084.7907150256" test_time="0" test_result="true" id="86baaeb9-1688-4af4-883c-94a107c5f147" />
                                                                           </seq>
                                                                     </dec>
                                                                     <dec name="T" x="2724.7348980299707" y="942.9157150255986"> 
                                                                           <par name="TimeControl" x="2694.2348980299707" y="1008.6657150255988" collapsed="false" id="224864b1-7470-4787-8dd4-b3fb8b794e44"> 
                                                                                 <seq name="OperatorRequest" x="2594.2348980299703" y="1090.6657150255985" collapsed="false" id="89afdcc7-1852-4bdd-89f2-83eeed906fb5"> 
                                                                                       <tsk name="PushHMI(data=panoramic_image)" x="2335.234898029974" y="1149.6657150256" test_time="0" test_result="true" id="e3174ab9-4247-4ebd-98e3-4f4831649e50" />
                                                                                       <tsk name="PushHMI(data=occupancy_grid)" x="2382.234898029972" y="1188.6657150256012" test_time="0" test_result="true" id="dc2dd19f-1e0a-4b2b-993a-2f43f25a28fc" />
                                                                                       <tsk name="PushHMI(data=path)" x="2482.2348980299726" y="1230.6657150256012" test_time="0" test_result="true" id="a0cf1cb2-89d2-4762-839b-bb72952588b9" />
                                                                                       <tsk name="HMIResponce" x="2644.2348980299707" y="1227.6657150256012" test_time="0" test_result="true" id="8c9d1f1d-b1d6-4a8f-8cd1-3f3ca0098e29" />
                                                                                 </seq>
                                                                                 <tsk name="Monitor(target=Timeout)" x="2689.2348980299707" y="1136.6657150256" test_time="0" test_result="true" id="4296f98c-feee-4b85-9ff0-f59a6965a574" />
                                                                           </par>
                                                                     </dec>
                                                                  </par>
                                                            </sel>
                                                      </par>
                                                </dec>
                                                   <par name="TrackObjectAndGoToIt" x="2725.1349008049774" y="661.0753331852221" collapsed="false" id="f33510ef-230c-49d4-87da-24bef8ccc485"> 
                                                         <tsk name="TrackObject(target=Spigot)" x="2666.4480321181068" y="742.9440200539087" test_time="0" test_result="true" id="d7f651b6-414e-4b73-9c96-78bb08333ad3" />
                                                         <seq name="SearchPathAndGo" x="2834.8202154902915" y="742.6837247936138" collapsed="false" id="653e8f9e-51d2-4a48-83ab-14aa425649f2"> 
                                                               <par name="OperatorCheckPoint" x="2598.3598980299703" y="868.9157150256027" collapsed="true" id="81d5fc0e-0ec0-485a-a70d-39883e2686f9"> 
                                                                  <dec name="L" x="2572.609898029971" y="940.9157150255988"> 
                                                                        <seq name="Stabilization" x="2542.109898029971" y="1004.7907150255988" collapsed="true" id="080f208e-28c9-48b8-8754-1bd9ccc4ca57"> 
                                                                              <tsk name="Monitor(target=Stable)" x="2424.359898029972" y="1085.1657150256" test_time="0" test_result="true" id="4382b9bf-54e7-419a-851e-0a07c63d2a76" />
                                                                              <tsk name="PostureControl(pose=stabilization)" x="2582.1098980299707" y="1084.7907150256" test_time="0" test_result="true" id="86baaeb9-1688-4af4-883c-94a107c5f147" />
                                                                        </seq>
                                                                  </dec>
                                                                  <dec name="T" x="2724.7348980299707" y="942.9157150255986"> 
                                                                        <par name="TimeControl" x="2694.2348980299707" y="1008.6657150255988" collapsed="false" id="224864b1-7470-4787-8dd4-b3fb8b794e44"> 
                                                                              <seq name="OperatorRequest" x="2594.2348980299703" y="1090.6657150255985" collapsed="false" id="89afdcc7-1852-4bdd-89f2-83eeed906fb5"> 
                                                                                    <tsk name="PushHMI(data=panoramic_image)" x="2335.234898029974" y="1149.6657150256" test_time="0" test_result="true" id="e3174ab9-4247-4ebd-98e3-4f4831649e50" />
                                                                                    <tsk name="PushHMI(data=occupancy_grid)" x="2382.234898029972" y="1188.6657150256012" test_time="0" test_result="true" id="dc2dd19f-1e0a-4b2b-993a-2f43f25a28fc" />
                                                                                    <tsk name="PushHMI(data=path)" x="2482.2348980299726" y="1230.6657150256012" test_time="0" test_result="true" id="a0cf1cb2-89d2-4762-839b-bb72952588b9" />
                                                                                    <tsk name="HMIResponce" x="2644.2348980299707" y="1227.6657150256012" test_time="0" test_result="true" id="8c9d1f1d-b1d6-4a8f-8cd1-3f3ca0098e29" />
                                                                              </seq>
                                                                              <tsk name="Monitor(target=Timeout)" x="2689.2348980299707" y="1136.6657150256" test_time="0" test_result="true" id="4296f98c-feee-4b85-9ff0-f59a6965a574" />
                                                                        </par>
                                                                  </dec>
                                                               </par>
                                                               <tsk name="PerceptionCalibration" x="2776.250291375286" y="844.8406038405916" test_time="0" test_result="true" id="1ea0e604-b442-4af9-b3b0-f9637c40f1dc" />
                                                               <tsk name="PathPlanningFocus(target=Spigot)" x="2820.5125231825978" y="881.9914171013028" test_time="0" test_result="true" id="e551730c-a2aa-40ca-af4b-6ba4d4b3f299" />
                                                               <tsk name="TurnTo(target=Spigot)" x="2863.58944625952" y="918.9144940243795" test_time="0" test_result="true" id="d29467b4-de1f-40d5-9363-eb1a6ff1aa1e" />
                                                            <dec name="!L!" x="3040.633470351374" y="885.3837607479933"> 
                                                                  <swi name="Move" x="3034.584867504943" y="949.6883035481891" collapsed="false" id="5a9d04be-4f89-4575-89ca-ff9f190415f9"> 
                                                                        <par name="AdvanceByWalkingAlongPath" x="2860.584867504941" y="1021.68830354819" collapsed="false" id="6ebd159a-f2a2-4d9d-983a-f70d8ef135b1"> 
                                                                           <dec name="!L!" x="2801.484413462348" y="1076.9904523580867"> 
                                                                                 <seq name="PedestrianWalk" x="2766.1391753671114" y="1144.053944421578" collapsed="false" id="546dcdb6-af55-4307-9e9c-5ca0d9b22b49"> 
                                                                                    <jnt x="2222.6423853923834" y="1368.9472749472716" > 
                                                                                          <sel name="PathFollow" x="2140.6576430105833" y="1409.3392702069013" collapsed="false" id="944aa348-6c23-48fc-8e86-f5ffbe5e9f4c"> 
                                                                                                <par name="Dynamic" x="1906.4072822602207" y="1564.4698618375037" collapsed="false" id="c62c576f-78bc-4e87-b611-98c41f13ce26"> 
                                                                                                   <dec name="F:1" x="1875.6850649350624" y="1608.089854589848"> 
                                                                                                         <tsk name="whileDynamicWalk" x="1828.6295044824415" y="1657.803195170833" test_time="0" test_result="true" id="b4c6f4ca-277d-4d6d-bd85-9d750f52f7a8" />
                                                                                                   </dec>
                                                                                                      <sel name="Try" x="1970.3822843822845" y="1657.4119214119182" collapsed="false" id="5c14a900-5e51-4cff-abc7-e676fe221c09"> 
                                                                                                            <seq name="DynamicWalkTask" x="1820.2711732711718" y="1715.6341436341386" collapsed="false" id="79cbd549-751d-40ee-8b20-d05ec87448e6"> 
                                                                                                                  <tsk name="DWStandUp" x="1779.2711732711718" y="1771.6341436341386" test_time="0" test_result="true" id="4f7aab64-539a-4b5a-80f8-46f0098e7a80" />
                                                                                                                  <tsk name="DynamicWalk" x="1871.6295044824426" y="1772.3587507263846" test_time="0" test_result="true" id="b262874d-f313-428b-b0ab-307da4d5ce23" />
                                                                                                            </seq>
                                                                                                            <tsk name="QuadWalk(mode=DEBRIS)" x="1943.5183933713286" y="1713.8031951708317" test_time="0" test_result="true" id="161b819e-2d6b-4bd8-83e8-0b5e7b616a66" />
                                                                                                      </sel>
                                                                                                </par>
                                                                                                <par name="Discrete" x="2139.296171149107" y="1564.0254173930598" collapsed="false" id="08f23f0a-0be6-4b70-90c9-ad1337e4e62a"> 
                                                                                                   <dec name="F:1" x="2096.685064935063" y="1607.7565212565146"> 
                                                                                                         <tsk name="whileDiscreteWalk" x="2054.5183933713297" y="1655.3587507263915" test_time="0" test_result="true" id="60f61308-56a5-4335-a648-795690e62393" />
                                                                                                   </dec>
                                                                                                      <sel name="Try" x="2197.0489510489488" y="1655.189699189696" collapsed="false" id="5d0244bb-a35f-451c-ad77-a66d8e3e3c2b"> 
                                                                                                            <seq name="DiscreteWalkTask" x="2120.2711732711714" y="1708.6341436341386" collapsed="false" id="0a5da691-eb1f-4465-8787-7a46d67fe678"> 
                                                                                                                  <tsk name="DWStandUp" x="2098.2711732711714" y="1772.6341436341386" test_time="0" test_result="true" id="467e98ae-cbdc-4ec4-976c-6c0cab8940a8" />
                                                                                                                  <tsk name="DiscreteWalk" x="2186.073948926888" y="1773.1365285041634" test_time="0" test_result="true" id="00607f67-1e5a-4174-8c5f-1980f00e0680" />
                                                                                                            </seq>
                                                                                                            <sel name="try_quads" x="2298.573948926887" y="1710.3031951708344" collapsed="false" id="11e38bcb-c2db-451d-8107-0016eace52ce"> 
                                                                                                                  <par name="Debris" x="2305.9628378157745" y="1769.9143062819471" collapsed="false" id="06a6691d-bb10-4701-942c-b9bd8827c7fd"> 
                                                                                                                     <dec name="F:1" x="2261.907287157283" y="1815.7565212565137"> 
                                                                                                                           <tsk name="whileQuadWalkDEBRIS" x="2208.1850600379967" y="1863.2476396152765" test_time="0" test_result="true" id="12b76090-0766-4af5-aa5c-f87a8692c335" />
                                                                                                                     </dec>
                                                                                                                        <tsk name="QuadWalk(mode=DEBRIS)" x="2357.851726704663" y="1866.1365285041634" test_time="0" test_result="true" id="99191540-18e7-4148-b56c-a4b0b994085b" />
                                                                                                                  </par>
                                                                                                                  <tsk name="QuadWalk(mode=HILLS)" x="2373.5183933713297" y="1770.247639615277" test_time="0" test_result="true" id="934886f6-fa30-4bbb-8538-26e4a0998150" />
                                                                                                            </sel>
                                                                                                      </sel>
                                                                                                </par>
                                                                                                <par name="Quad_MUD" x="2374.8517267046614" y="1560.6920840597268" collapsed="false" id="1eb74863-3986-4aba-b8f3-1197ee16c3bb"> 
                                                                                                   <dec name="F:1" x="2332.2406204906174" y="1604.4231879231816"> 
                                                                                                         <tsk name="whileQuadWalkMUD" x="2290.0739489268844" y="1652.0254173930584" test_time="0" test_result="true" id="0918f43a-0853-4ade-9014-5d74dd42261f" />
                                                                                                   </dec>
                                                                                                      <tsk name="QuadWalk(mode=MUD)" x="2421.629504482439" y="1651.8031951708308" test_time="0" test_result="true" id="218a31c2-d2de-41e5-bb1c-918d8c572707" />
                                                                                                </par>
                                                                                          </sel>
                                                                                    </jnt>
                                                                                 </seq>
                                                                           </dec>
                                                                              <par name="Exceptions" x="3001.7692386893104" y="1079.496606356488" collapsed="false" id="4c27cb0a-465c-4244-be43-91a86e04ea5d"> 
                                                                                 <dec name="F:1" x="2993.542875680342" y="1127.4727968326818"> 
                                                                                       <tsk name="untilOperatorIntervention" x="2929.0717550135723" y="1184.4203601389277" test_time="0" test_result="true" id="f824ca65-3c8c-4494-902c-5ef4893153a9" />
                                                                                 </dec>
                                                                                 <dec name="F:1" x="3046.2533656734367" y="1128.306130166013"> 
                                                                                       <tsk name="whileSolution" x="3017.45605187613" y="1230.6024751253944" test_time="0" test_result="true" id="d5705725-a5bd-4ebe-96c9-12ae4b97d2b9" />
                                                                                 </dec>
                                                                              </par>
                                                                        </par>
                                                                        <seq name="NoSolution" x="3125.1802045350605" y="1126.9500249186121" collapsed="true" id="4fd869ea-12a8-46d1-9072-687887477aa1"> 
                                                                              <par name="OperatorControlPoint" x="3095.3468712017248" y="1209.9500249186106" collapsed="false" id="c0f5918f-5569-4793-88b2-4a51928e1c24"> 
                                                                                 <dec name="L" x="3061.680204535056" y="1258.2833582519427"> 
                                                                                       <seq name="Stabilization" x="3030.680204535057" y="1305.2833582519409" collapsed="false" id="7ffbdf8d-e623-40d9-89da-884e5ca8e9b2"> 
                                                                                             <tsk name="Monitor(target=Stable)" x="2989.6802045350587" y="1346.2833582519384" test_time="0" test_result="true" id="d7a6447c-69aa-462e-9ec1-aeca06a6600c" />
                                                                                             <tsk name="PostureControl(pose=stabilization)" x="3041.6802045350587" y="1380.2833582519374" test_time="0" test_result="true" id="a63a2ecf-35da-426e-952e-71e9d3a6e24d" />
                                                                                       </seq>
                                                                                 </dec>
                                                                                 <dec name="T" x="3264.846871201731" y="1260.6166915852743"> 
                                                                                       <par name="TimeControl" x="3235.180204535064" y="1358.450024918608" collapsed="false" id="3dfb5281-fa21-4182-83a4-314b17d7616f"> 
                                                                                             <seq name="OperatorRequest" x="3166.6802045350632" y="1427.283358251941" collapsed="false" id="7e00ab21-1315-4ed7-b170-b6747a0f8cf2"> 
                                                                                                   <tsk name="PushHMI(data=panoramic_image)" x="3131.6802045350614" y="1472.2833582519415" test_time="0" test_result="true" id="9a5b4f2f-3872-4a5e-869b-b1d0bfec39c3" />
                                                                                                   <tsk name="HMIResponce" x="3273.6802045350605" y="1506.2833582519415" test_time="0" test_result="true" id="8cfc56cd-d295-40ac-b8ae-831ec4bba54d" />
                                                                                             </seq>
                                                                                             <tsk name="Monitor(target=Timeout)" x="3326.8468712017266" y="1430.9500249186099" test_time="0" test_result="true" id="d715e294-e049-40fc-ac75-9a1d0802f87b" />
                                                                                       </par>
                                                                                 </dec>
                                                                              </par>
                                                                        </seq>
                                                                  </swi>
                                                            </dec>
                                                         </seq>
                                                   </par>
                                             </seq>
                                             <seq name="OpenSpigotSequance" x="2743.9591346274233" y="526.9666111710859" collapsed="true" id="fc1afb10-f824-42e9-91bb-2aae8fc7201f"> 
                                                   <par name="StabilizationDuringOpenning" x="2734.79290727892" y="583.3762234026752" collapsed="false" id="aad9ddad-6e03-4581-a7d0-6457c2ab523b"> 
                                                         <seq name="Stabilization" x="2650.126240612251" y="653.3762234026759" collapsed="false" id="5e64e924-9109-49ff-a821-28fb69c1e200"> 
                                                               <tsk name="Monitor(target=Stable)" x="2462.126240612254" y="735.3762234026766" test_time="-1" test_result="true" id="47eb89db-feaa-43c3-b5c4-3f25646f074b" />
                                                               <tsk name="PostureControl(pose=stabilize)" x="2613.1262406122514" y="736.3762234026766" test_time="100" test_result="true" id="a4955685-a4cd-4413-aec8-a529c07847c9" />
                                                         </seq>
                                                         <tsk name="OpenSpigot" x="2772.6884226884167" y="653.3027250527185" test_time="0" test_result="true" id="3be13d2d-c9a8-4f8e-b3ce-86029f9f47d4" />
                                                   </par>
                                             </seq>
                                       </seq>
                                 </seq>
                           </dec>
                        </par>
                  </seq>
            </dec>
         </par>
   </par>
</plan>